{
  "prediction_date": "2026-07-09",
  "config": "BB_Full+GPS",
  "data_hashes": {
    "usgs": "75fb67f98506630f",
    "jma": "6baa20492fea6d92",
    "gps": "1bded67b661b40a9"
  },
  "zones": [
    {
      "zone_id": "Z_15_120",
      "name": "Okinawa",
      "pop_millions": 28,
      "tiers": {
        "T1": {
          "probability": 0.024612,
          "alerts": {
            "0.5pct": false,
            "1.0pct": false,
            "2.0pct": false,
            "5.0pct": false,
            "10.0pct": false
          },
          "validity": {
            "window_days": 2,
            "valid_from": "2026-07-10T00:00:00Z",
            "valid_to": "2026-07-11T23:59:59Z"
          },
          "probability_seismic": 0.024612,
          "gps_reliability": 0.646,
          "boost": 0.0
        },
        "T2": {
          "probability": 0.222514,
          "alerts": {
            "0.5pct": false,
            "1.0pct": false,
            "2.0pct": false,
            "5.0pct": false,
            "10.0pct": false
          },
          "validity": {
            "window_days": 2,
            "valid_from": "2026-07-10T00:00:00Z",
            "valid_to": "2026-07-11T23:59:59Z"
          },
          "probability_seismic": 0.222514,
          "gps_reliability": 0.646,
          "boost": 0.0
        },
        "T3": {
          "probability": 0.312511,
          "alerts": {
            "0.5pct": false,
            "1.0pct": false,
            "2.0pct": false,
            "5.0pct": false,
            "10.0pct": false
          },
          "validity": {
            "window_days": 3,
            "valid_from": "2026-07-10T00:00:00Z",
            "valid_to": "2026-07-12T23:59:59Z"
          },
          "probability_seismic": 0.312511,
          "gps_reliability": 0.646,
          "boost": 0.0
        },
        "T4": {
          "probability": 0.286111,
          "alerts": {
            "0.5pct": false,
            "1.0pct": false,
            "2.0pct": false,
            "5.0pct": false,
            "10.0pct": false
          },
          "validity": {
            "window_days": 3,
            "valid_from": "2026-07-10T00:00:00Z",
            "valid_to": "2026-07-12T23:59:59Z"
          },
          "probability_seismic": 0.286111,
          "gps_reliability": 0.646,
          "boost": -0.0
        }
      }
    },
    {
      "zone_id": "Z_15_145",
      "name": "Z_15_145",
      "pop_millions": 0,
      "tiers": {
        "T1": {
          "probability": 0.025499,
          "alerts": {
            "0.5pct": false,
            "1.0pct": false,
            "2.0pct": false,
            "5.0pct": false,
            "10.0pct": false
          },
          "validity": {
            "window_days": 2,
            "valid_from": "2026-07-10T00:00:00Z",
            "valid_to": "2026-07-11T23:59:59Z"
          },
          "probability_seismic": 0.025499,
          "gps_reliability": 0.25,
          "boost": 0.0
        },
        "T2": {
          "probability": 0.230618,
          "alerts": {
            "0.5pct": false,
            "1.0pct": false,
            "2.0pct": false,
            "5.0pct": false,
            "10.0pct": false
          },
          "validity": {
            "window_days": 2,
            "valid_from": "2026-07-10T00:00:00Z",
            "valid_to": "2026-07-11T23:59:59Z"
          },
          "probability_seismic": 0.230618,
          "gps_reliability": 0.25,
          "boost": -0.0
        },
        "T3": {
          "probability": 0.320526,
          "alerts": {
            "0.5pct": false,
            "1.0pct": false,
            "2.0pct": false,
            "5.0pct": false,
            "10.0pct": false
          },
          "validity": {
            "window_days": 3,
            "valid_from": "2026-07-10T00:00:00Z",
            "valid_to": "2026-07-12T23:59:59Z"
          },
          "probability_seismic": 0.320526,
          "gps_reliability": 0.25,
          "boost": 0.0
        },
        "T4": {
          "probability": 0.292419,
          "alerts": {
            "0.5pct": false,
            "1.0pct": false,
            "2.0pct": false,
            "5.0pct": false,
            "10.0pct": false
          },
          "validity": {
            "window_days": 3,
            "valid_from": "2026-07-10T00:00:00Z",
            "valid_to": "2026-07-12T23:59:59Z"
          },
          "probability_seismic": 0.292419,
          "gps_reliability": 0.25,
          "boost": 0.0
        }
      }
    },
    {
      "zone_id": "Z_20_120",
      "name": "Ryukyu",
      "pop_millions": 8,
      "tiers": {
        "T1": {
          "probability": 0.556058,
          "alerts": {
            "0.5pct": false,
            "1.0pct": false,
            "2.0pct": false,
            "5.0pct": false,
            "10.0pct": false
          },
          "validity": {
            "window_days": 2,
            "valid_from": "2026-07-10T00:00:00Z",
            "valid_to": "2026-07-11T23:59:59Z"
          },
          "probability_seismic": 0.556058,
          "gps_reliability": 0.5,
          "boost": 0.0
        },
        "T2": {
          "probability": 0.591242,
          "alerts": {
            "0.5pct": false,
            "1.0pct": false,
            "2.0pct": false,
            "5.0pct": false,
            "10.0pct": false
          },
          "validity": {
            "window_days": 2,
            "valid_from": "2026-07-10T00:00:00Z",
            "valid_to": "2026-07-11T23:59:59Z"
          },
          "probability_seismic": 0.591242,
          "gps_reliability": 0.5,
          "boost": 0.0
        },
        "T3": {
          "probability": 0.539793,
          "alerts": {
            "0.5pct": false,
            "1.0pct": false,
            "2.0pct": false,
            "5.0pct": false,
            "10.0pct": false
          },
          "validity": {
            "window_days": 3,
            "valid_from": "2026-07-10T00:00:00Z",
            "valid_to": "2026-07-12T23:59:59Z"
          },
          "probability_seismic": 0.539793,
          "gps_reliability": 0.5,
          "boost": 0.0
        },
        "T4": {
          "probability": 0.460167,
          "alerts": {
            "0.5pct": false,
            "1.0pct": false,
            "2.0pct": false,
            "5.0pct": false,
            "10.0pct": false
          },
          "validity": {
            "window_days": 3,
            "valid_from": "2026-07-10T00:00:00Z",
            "valid_to": "2026-07-12T23:59:59Z"
          },
          "probability_seismic": 0.460167,
          "gps_reliability": 0.5,
          "boost": 0.0
        }
      }
    },
    {
      "zone_id": "Z_20_125",
      "name": "Z_20_125",
      "pop_millions": 0,
      "tiers": {
        "T1": {
          "probability": 0.212239,
          "alerts": {
            "0.5pct": false,
            "1.0pct": false,
            "2.0pct": false,
            "5.0pct": false,
            "10.0pct": false
          },
          "validity": {
            "window_days": 2,
            "valid_from": "2026-07-10T00:00:00Z",
            "valid_to": "2026-07-11T23:59:59Z"
          },
          "probability_seismic": 0.212239,
          "gps_reliability": 0.25,
          "boost": -0.0
        },
        "T2": {
          "probability": 0.161644,
          "alerts": {
            "0.5pct": false,
            "1.0pct": false,
            "2.0pct": false,
            "5.0pct": false,
            "10.0pct": false
          },
          "validity": {
            "window_days": 2,
            "valid_from": "2026-07-10T00:00:00Z",
            "valid_to": "2026-07-11T23:59:59Z"
          },
          "probability_seismic": 0.161644,
          "gps_reliability": 0.25,
          "boost": -0.0
        },
        "T3": {
          "probability": 0.176056,
          "alerts": {
            "0.5pct": false,
            "1.0pct": false,
            "2.0pct": false,
            "5.0pct": false,
            "10.0pct": false
          },
          "validity": {
            "window_days": 3,
            "valid_from": "2026-07-10T00:00:00Z",
            "valid_to": "2026-07-12T23:59:59Z"
          },
          "probability_seismic": 0.176056,
          "gps_reliability": 0.25,
          "boost": 0.0
        },
        "T4": {
          "probability": 0.124332,
          "alerts": {
            "0.5pct": false,
            "1.0pct": false,
            "2.0pct": false,
            "5.0pct": false,
            "10.0pct": false
          },
          "validity": {
            "window_days": 3,
            "valid_from": "2026-07-10T00:00:00Z",
            "valid_to": "2026-07-12T23:59:59Z"
          },
          "probability_seismic": 0.124332,
          "gps_reliability": 0.25,
          "boost": 0.0
        }
      }
    },
    {
      "zone_id": "Z_20_140",
      "name": "Z_20_140",
      "pop_millions": 0,
      "tiers": {
        "T1": {
          "probability": 0.055038,
          "alerts": {
            "0.5pct": false,
            "1.0pct": false,
            "2.0pct": false,
            "5.0pct": false,
            "10.0pct": false
          },
          "validity": {
            "window_days": 2,
            "valid_from": "2026-07-10T00:00:00Z",
            "valid_to": "2026-07-11T23:59:59Z"
          },
          "probability_seismic": 0.055038,
          "gps_reliability": 0.396,
          "boost": 0.0
        },
        "T2": {
          "probability": 0.262501,
          "alerts": {
            "0.5pct": false,
            "1.0pct": false,
            "2.0pct": false,
            "5.0pct": false,
            "10.0pct": false
          },
          "validity": {
            "window_days": 2,
            "valid_from": "2026-07-10T00:00:00Z",
            "valid_to": "2026-07-11T23:59:59Z"
          },
          "probability_seismic": 0.262501,
          "gps_reliability": 0.396,
          "boost": -0.0
        },
        "T3": {
          "probability": 0.337098,
          "alerts": {
            "0.5pct": false,
            "1.0pct": false,
            "2.0pct": false,
            "5.0pct": false,
            "10.0pct": false
          },
          "validity": {
            "window_days": 3,
            "valid_from": "2026-07-10T00:00:00Z",
            "valid_to": "2026-07-12T23:59:59Z"
          },
          "probability_seismic": 0.337098,
          "gps_reliability": 0.396,
          "boost": -0.0
        },
        "T4": {
          "probability": 0.252153,
          "alerts": {
            "0.5pct": false,
            "1.0pct": false,
            "2.0pct": false,
            "5.0pct": false,
            "10.0pct": false
          },
          "validity": {
            "window_days": 3,
            "valid_from": "2026-07-10T00:00:00Z",
            "valid_to": "2026-07-12T23:59:59Z"
          },
          "probability_seismic": 0.252153,
          "gps_reliability": 0.396,
          "boost": 0.0
        }
      }
    },
    {
      "zone_id": "Z_20_145",
      "name": "Z_20_145",
      "pop_millions": 0,
      "tiers": {
        "T1": {
          "probability": 0.101433,
          "alerts": {
            "0.5pct": false,
            "1.0pct": false,
            "2.0pct": false,
            "5.0pct": false,
            "10.0pct": true
          },
          "validity": {
            "window_days": 2,
            "valid_from": "2026-07-10T00:00:00Z",
            "valid_to": "2026-07-11T23:59:59Z"
          }
        },
        "T2": {
          "probability": 0.388348,
          "alerts": {
            "0.5pct": false,
            "1.0pct": false,
            "2.0pct": false,
            "5.0pct": false,
            "10.0pct": true
          },
          "validity": {
            "window_days": 2,
            "valid_from": "2026-07-10T00:00:00Z",
            "valid_to": "2026-07-11T23:59:59Z"
          }
        },
        "T3": {
          "probability": 0.465411,
          "alerts": {
            "0.5pct": false,
            "1.0pct": false,
            "2.0pct": false,
            "5.0pct": true,
            "10.0pct": true
          },
          "validity": {
            "window_days": 3,
            "valid_from": "2026-07-10T00:00:00Z",
            "valid_to": "2026-07-12T23:59:59Z"
          }
        },
        "T4": {
          "probability": 0.461208,
          "alerts": {
            "0.5pct": false,
            "1.0pct": false,
            "2.0pct": true,
            "5.0pct": true,
            "10.0pct": true
          },
          "validity": {
            "window_days": 3,
            "valid_from": "2026-07-10T00:00:00Z",
            "valid_to": "2026-07-12T23:59:59Z"
          }
        }
      }
    },
    {
      "zone_id": "Z_25_120",
      "name": "Z_25_120",
      "pop_millions": 2,
      "tiers": {
        "T1": {
          "probability": 0.244884,
          "alerts": {
            "0.5pct": false,
            "1.0pct": false,
            "2.0pct": false,
            "5.0pct": false,
            "10.0pct": false
          },
          "validity": {
            "window_days": 2,
            "valid_from": "2026-07-10T00:00:00Z",
            "valid_to": "2026-07-11T23:59:59Z"
          },
          "probability_seismic": 0.244884,
          "gps_reliability": 0.896,
          "boost": -0.0
        },
        "T2": {
          "probability": 0.179718,
          "alerts": {
            "0.5pct": false,
            "1.0pct": false,
            "2.0pct": false,
            "5.0pct": false,
            "10.0pct": false
          },
          "validity": {
            "window_days": 2,
            "valid_from": "2026-07-10T00:00:00Z",
            "valid_to": "2026-07-11T23:59:59Z"
          },
          "probability_seismic": 0.179718,
          "gps_reliability": 0.896,
          "boost": 0.0
        },
        "T3": {
          "probability": 0.119081,
          "alerts": {
            "0.5pct": false,
            "1.0pct": false,
            "2.0pct": false,
            "5.0pct": false,
            "10.0pct": false
          },
          "validity": {
            "window_days": 3,
            "valid_from": "2026-07-10T00:00:00Z",
            "valid_to": "2026-07-12T23:59:59Z"
          },
          "probability_seismic": 0.119081,
          "gps_reliability": 0.896,
          "boost": -0.0
        },
        "T4": {
          "probability": 0.108837,
          "alerts": {
            "0.5pct": false,
            "1.0pct": false,
            "2.0pct": false,
            "5.0pct": false,
            "10.0pct": false
          },
          "validity": {
            "window_days": 3,
            "valid_from": "2026-07-10T00:00:00Z",
            "valid_to": "2026-07-12T23:59:59Z"
          },
          "probability_seismic": 0.108837,
          "gps_reliability": 0.896,
          "boost": 0.0
        }
      }
    },
    {
      "zone_id": "Z_25_125",
      "name": "Z_25_125",
      "pop_millions": 0,
      "tiers": {
        "T1": {
          "probability": 0.550984,
          "alerts": {
            "0.5pct": false,
            "1.0pct": false,
            "2.0pct": false,
            "5.0pct": false,
            "10.0pct": false
          },
          "validity": {
            "window_days": 2,
            "valid_from": "2026-07-10T00:00:00Z",
            "valid_to": "2026-07-11T23:59:59Z"
          },
          "probability_seismic": 0.550984,
          "gps_reliability": 0.25,
          "boost": 0.0
        },
        "T2": {
          "probability": 0.28891,
          "alerts": {
            "0.5pct": false,
            "1.0pct": false,
            "2.0pct": false,
            "5.0pct": false,
            "10.0pct": false
          },
          "validity": {
            "window_days": 2,
            "valid_from": "2026-07-10T00:00:00Z",
            "valid_to": "2026-07-11T23:59:59Z"
          },
          "probability_seismic": 0.28891,
          "gps_reliability": 0.25,
          "boost": 0.0
        },
        "T3": {
          "probability": 0.177951,
          "alerts": {
            "0.5pct": false,
            "1.0pct": false,
            "2.0pct": false,
            "5.0pct": false,
            "10.0pct": false
          },
          "validity": {
            "window_days": 3,
            "valid_from": "2026-07-10T00:00:00Z",
            "valid_to": "2026-07-12T23:59:59Z"
          },
          "probability_seismic": 0.177951,
          "gps_reliability": 0.25,
          "boost": 0.0
        },
        "T4": {
          "probability": 0.134839,
          "alerts": {
            "0.5pct": false,
            "1.0pct": false,
            "2.0pct": false,
            "5.0pct": false,
            "10.0pct": false
          },
          "validity": {
            "window_days": 3,
            "valid_from": "2026-07-10T00:00:00Z",
            "valid_to": "2026-07-12T23:59:59Z"
          },
          "probability_seismic": 0.134839,
          "gps_reliability": 0.25,
          "boost": 0.0
        }
      }
    },
    {
      "zone_id": "Z_25_130",
      "name": "Z_25_130",
      "pop_millions": 0,
      "tiers": {
        "T1": {
          "probability": 0.46684,
          "alerts": {
            "0.5pct": false,
            "1.0pct": false,
            "2.0pct": false,
            "5.0pct": false,
            "10.0pct": false
          },
          "validity": {
            "window_days": 2,
            "valid_from": "2026-07-10T00:00:00Z",
            "valid_to": "2026-07-11T23:59:59Z"
          },
          "probability_seismic": 0.46684,
          "gps_reliability": 0.5,
          "boost": 0.0
        },
        "T2": {
          "probability": 0.224432,
          "alerts": {
            "0.5pct": false,
            "1.0pct": false,
            "2.0pct": false,
            "5.0pct": false,
            "10.0pct": false
          },
          "validity": {
            "window_days": 2,
            "valid_from": "2026-07-10T00:00:00Z",
            "valid_to": "2026-07-11T23:59:59Z"
          },
          "probability_seismic": 0.224432,
          "gps_reliability": 0.5,
          "boost": 0.0
        },
        "T3": {
          "probability": 0.14131,
          "alerts": {
            "0.5pct": false,
            "1.0pct": false,
            "2.0pct": false,
            "5.0pct": false,
            "10.0pct": false
          },
          "validity": {
            "window_days": 3,
            "valid_from": "2026-07-10T00:00:00Z",
            "valid_to": "2026-07-12T23:59:59Z"
          },
          "probability_seismic": 0.14131,
          "gps_reliability": 0.5,
          "boost": 0.0
        },
        "T4": {
          "probability": 0.106504,
          "alerts": {
            "0.5pct": false,
            "1.0pct": false,
            "2.0pct": false,
            "5.0pct": false,
            "10.0pct": false
          },
          "validity": {
            "window_days": 3,
            "valid_from": "2026-07-10T00:00:00Z",
            "valid_to": "2026-07-12T23:59:59Z"
          },
          "probability_seismic": 0.106504,
          "gps_reliability": 0.5,
          "boost": 0.0
        }
      }
    },
    {
      "zone_id": "Z_25_135",
      "name": "Z_25_135",
      "pop_millions": 0,
      "tiers": {
        "T1": {
          "probability": 0.078462,
          "alerts": {
            "0.5pct": false,
            "1.0pct": false,
            "2.0pct": false,
            "5.0pct": false,
            "10.0pct": false
          },
          "validity": {
            "window_days": 2,
            "valid_from": "2026-07-10T00:00:00Z",
            "valid_to": "2026-07-11T23:59:59Z"
          }
        },
        "T2": {
          "probability": 0.310517,
          "alerts": {
            "0.5pct": false,
            "1.0pct": false,
            "2.0pct": false,
            "5.0pct": false,
            "10.0pct": false
          },
          "validity": {
            "window_days": 2,
            "valid_from": "2026-07-10T00:00:00Z",
            "valid_to": "2026-07-11T23:59:59Z"
          }
        },
        "T3": {
          "probability": 0.38431,
          "alerts": {
            "0.5pct": false,
            "1.0pct": false,
            "2.0pct": false,
            "5.0pct": false,
            "10.0pct": false
          },
          "validity": {
            "window_days": 3,
            "valid_from": "2026-07-10T00:00:00Z",
            "valid_to": "2026-07-12T23:59:59Z"
          }
        },
        "T4": {
          "probability": 0.355691,
          "alerts": {
            "0.5pct": false,
            "1.0pct": false,
            "2.0pct": false,
            "5.0pct": false,
            "10.0pct": false
          },
          "validity": {
            "window_days": 3,
            "valid_from": "2026-07-10T00:00:00Z",
            "valid_to": "2026-07-12T23:59:59Z"
          }
        }
      }
    },
    {
      "zone_id": "Z_25_140",
      "name": "Z_25_140",
      "pop_millions": 0,
      "tiers": {
        "T1": {
          "probability": 0.34789,
          "alerts": {
            "0.5pct": false,
            "1.0pct": false,
            "2.0pct": false,
            "5.0pct": false,
            "10.0pct": false
          },
          "validity": {
            "window_days": 2,
            "valid_from": "2026-07-10T00:00:00Z",
            "valid_to": "2026-07-11T23:59:59Z"
          },
          "probability_seismic": 0.34789,
          "gps_reliability": 0.5,
          "boost": 0.0
        },
        "T2": {
          "probability": 0.684691,
          "alerts": {
            "0.5pct": false,
            "1.0pct": false,
            "2.0pct": false,
            "5.0pct": false,
            "10.0pct": false
          },
          "validity": {
            "window_days": 2,
            "valid_from": "2026-07-10T00:00:00Z",
            "valid_to": "2026-07-11T23:59:59Z"
          },
          "probability_seismic": 0.684691,
          "gps_reliability": 0.5,
          "boost": 0.0
        },
        "T3": {
          "probability": 0.661419,
          "alerts": {
            "0.5pct": false,
            "1.0pct": false,
            "2.0pct": false,
            "5.0pct": false,
            "10.0pct": false
          },
          "validity": {
            "window_days": 3,
            "valid_from": "2026-07-10T00:00:00Z",
            "valid_to": "2026-07-12T23:59:59Z"
          },
          "probability_seismic": 0.661419,
          "gps_reliability": 0.5,
          "boost": 0.0
        },
        "T4": {
          "probability": 0.614621,
          "alerts": {
            "0.5pct": false,
            "1.0pct": false,
            "2.0pct": false,
            "5.0pct": false,
            "10.0pct": false
          },
          "validity": {
            "window_days": 3,
            "valid_from": "2026-07-10T00:00:00Z",
            "valid_to": "2026-07-12T23:59:59Z"
          },
          "probability_seismic": 0.614621,
          "gps_reliability": 0.5,
          "boost": 0.0
        }
      }
    },
    {
      "zone_id": "Z_30_125",
      "name": "Z_30_125",
      "pop_millions": 0,
      "tiers": {
        "T1": {
          "probability": 0.30076,
          "alerts": {
            "0.5pct": false,
            "1.0pct": false,
            "2.0pct": false,
            "5.0pct": false,
            "10.0pct": false
          },
          "validity": {
            "window_days": 2,
            "valid_from": "2026-07-10T00:00:00Z",
            "valid_to": "2026-07-11T23:59:59Z"
          },
          "probability_seismic": 0.30076,
          "gps_reliability": 1.0,
          "boost": 0.0
        },
        "T2": {
          "probability": 0.178913,
          "alerts": {
            "0.5pct": false,
            "1.0pct": false,
            "2.0pct": false,
            "5.0pct": false,
            "10.0pct": false
          },
          "validity": {
            "window_days": 2,
            "valid_from": "2026-07-10T00:00:00Z",
            "valid_to": "2026-07-11T23:59:59Z"
          },
          "probability_seismic": 0.178913,
          "gps_reliability": 1.0,
          "boost": 0.0
        },
        "T3": {
          "probability": 0.102329,
          "alerts": {
            "0.5pct": false,
            "1.0pct": false,
            "2.0pct": false,
            "5.0pct": false,
            "10.0pct": false
          },
          "validity": {
            "window_days": 3,
            "valid_from": "2026-07-10T00:00:00Z",
            "valid_to": "2026-07-12T23:59:59Z"
          },
          "probability_seismic": 0.102329,
          "gps_reliability": 1.0,
          "boost": 0.0
        },
        "T4": {
          "probability": 0.091874,
          "alerts": {
            "0.5pct": false,
            "1.0pct": false,
            "2.0pct": false,
            "5.0pct": false,
            "10.0pct": false
          },
          "validity": {
            "window_days": 3,
            "valid_from": "2026-07-10T00:00:00Z",
            "valid_to": "2026-07-12T23:59:59Z"
          },
          "probability_seismic": 0.091874,
          "gps_reliability": 1.0,
          "boost": -0.0
        }
      }
    },
    {
      "zone_id": "Z_30_130",
      "name": "Kyushu-South",
      "pop_millions": 13,
      "tiers": {
        "T1": {
          "probability": 0.391673,
          "alerts": {
            "0.5pct": false,
            "1.0pct": false,
            "2.0pct": false,
            "5.0pct": false,
            "10.0pct": false
          },
          "validity": {
            "window_days": 2,
            "valid_from": "2026-07-10T00:00:00Z",
            "valid_to": "2026-07-11T23:59:59Z"
          },
          "probability_seismic": 0.391673,
          "gps_reliability": 0.396,
          "boost": 0.0
        },
        "T2": {
          "probability": 0.163131,
          "alerts": {
            "0.5pct": false,
            "1.0pct": false,
            "2.0pct": false,
            "5.0pct": false,
            "10.0pct": false
          },
          "validity": {
            "window_days": 2,
            "valid_from": "2026-07-10T00:00:00Z",
            "valid_to": "2026-07-11T23:59:59Z"
          },
          "probability_seismic": 0.163131,
          "gps_reliability": 0.396,
          "boost": 0.0
        },
        "T3": {
          "probability": 0.079594,
          "alerts": {
            "0.5pct": false,
            "1.0pct": false,
            "2.0pct": false,
            "5.0pct": false,
            "10.0pct": false
          },
          "validity": {
            "window_days": 3,
            "valid_from": "2026-07-10T00:00:00Z",
            "valid_to": "2026-07-12T23:59:59Z"
          },
          "probability_seismic": 0.079594,
          "gps_reliability": 0.396,
          "boost": 0.0
        },
        "T4": {
          "probability": 0.057251,
          "alerts": {
            "0.5pct": false,
            "1.0pct": false,
            "2.0pct": false,
            "5.0pct": false,
            "10.0pct": false
          },
          "validity": {
            "window_days": 3,
            "valid_from": "2026-07-10T00:00:00Z",
            "valid_to": "2026-07-12T23:59:59Z"
          },
          "probability_seismic": 0.057251,
          "gps_reliability": 0.396,
          "boost": 0.0
        }
      }
    },
    {
      "zone_id": "Z_30_135",
      "name": "Kyushu-North",
      "pop_millions": 4,
      "tiers": {
        "T1": {
          "probability": 0.387317,
          "alerts": {
            "0.5pct": false,
            "1.0pct": false,
            "2.0pct": false,
            "5.0pct": false,
            "10.0pct": false
          },
          "validity": {
            "window_days": 2,
            "valid_from": "2026-07-10T00:00:00Z",
            "valid_to": "2026-07-11T23:59:59Z"
          },
          "probability_seismic": 0.387317,
          "gps_reliability": 0.25,
          "boost": 0.0
        },
        "T2": {
          "probability": 0.454124,
          "alerts": {
            "0.5pct": false,
            "1.0pct": false,
            "2.0pct": false,
            "5.0pct": false,
            "10.0pct": false
          },
          "validity": {
            "window_days": 2,
            "valid_from": "2026-07-10T00:00:00Z",
            "valid_to": "2026-07-11T23:59:59Z"
          },
          "probability_seismic": 0.454124,
          "gps_reliability": 0.25,
          "boost": 0.0
        },
        "T3": {
          "probability": 0.431398,
          "alerts": {
            "0.5pct": false,
            "1.0pct": false,
            "2.0pct": false,
            "5.0pct": false,
            "10.0pct": false
          },
          "validity": {
            "window_days": 3,
            "valid_from": "2026-07-10T00:00:00Z",
            "valid_to": "2026-07-12T23:59:59Z"
          },
          "probability_seismic": 0.431398,
          "gps_reliability": 0.25,
          "boost": 0.0
        },
        "T4": {
          "probability": 0.438196,
          "alerts": {
            "0.5pct": false,
            "1.0pct": false,
            "2.0pct": false,
            "5.0pct": false,
            "10.0pct": false
          },
          "validity": {
            "window_days": 3,
            "valid_from": "2026-07-10T00:00:00Z",
            "valid_to": "2026-07-12T23:59:59Z"
          },
          "probability_seismic": 0.438196,
          "gps_reliability": 0.25,
          "boost": 0.0
        }
      }
    },
    {
      "zone_id": "Z_30_140",
      "name": "Z_30_140",
      "pop_millions": 0,
      "tiers": {
        "T1": {
          "probability": 0.553325,
          "alerts": {
            "0.5pct": false,
            "1.0pct": false,
            "2.0pct": false,
            "5.0pct": false,
            "10.0pct": false
          },
          "validity": {
            "window_days": 2,
            "valid_from": "2026-07-10T00:00:00Z",
            "valid_to": "2026-07-11T23:59:59Z"
          }
        },
        "T2": {
          "probability": 0.372002,
          "alerts": {
            "0.5pct": false,
            "1.0pct": false,
            "2.0pct": false,
            "5.0pct": false,
            "10.0pct": false
          },
          "validity": {
            "window_days": 2,
            "valid_from": "2026-07-10T00:00:00Z",
            "valid_to": "2026-07-11T23:59:59Z"
          }
        },
        "T3": {
          "probability": 0.297074,
          "alerts": {
            "0.5pct": false,
            "1.0pct": false,
            "2.0pct": false,
            "5.0pct": false,
            "10.0pct": false
          },
          "validity": {
            "window_days": 3,
            "valid_from": "2026-07-10T00:00:00Z",
            "valid_to": "2026-07-12T23:59:59Z"
          }
        },
        "T4": {
          "probability": 0.26222,
          "alerts": {
            "0.5pct": false,
            "1.0pct": false,
            "2.0pct": false,
            "5.0pct": false,
            "10.0pct": false
          },
          "validity": {
            "window_days": 3,
            "valid_from": "2026-07-10T00:00:00Z",
            "valid_to": "2026-07-12T23:59:59Z"
          }
        }
      }
    },
    {
      "zone_id": "Z_35_130",
      "name": "Shikoku",
      "pop_millions": 8,
      "tiers": {
        "T1": {
          "probability": 0.222517,
          "alerts": {
            "0.5pct": false,
            "1.0pct": false,
            "2.0pct": false,
            "5.0pct": false,
            "10.0pct": false
          },
          "validity": {
            "window_days": 2,
            "valid_from": "2026-07-10T00:00:00Z",
            "valid_to": "2026-07-11T23:59:59Z"
          },
          "probability_seismic": 0.222517,
          "gps_reliability": 0.25,
          "boost": 0.0
        },
        "T2": {
          "probability": 0.177991,
          "alerts": {
            "0.5pct": false,
            "1.0pct": false,
            "2.0pct": false,
            "5.0pct": false,
            "10.0pct": false
          },
          "validity": {
            "window_days": 2,
            "valid_from": "2026-07-10T00:00:00Z",
            "valid_to": "2026-07-11T23:59:59Z"
          },
          "probability_seismic": 0.177991,
          "gps_reliability": 0.25,
          "boost": 0.0
        },
        "T3": {
          "probability": 0.221888,
          "alerts": {
            "0.5pct": false,
            "1.0pct": false,
            "2.0pct": false,
            "5.0pct": false,
            "10.0pct": true
          },
          "validity": {
            "window_days": 3,
            "valid_from": "2026-07-10T00:00:00Z",
            "valid_to": "2026-07-12T23:59:59Z"
          },
          "probability_seismic": 0.221888,
          "gps_reliability": 0.25,
          "boost": 0.0
        },
        "T4": {
          "probability": 0.18008,
          "alerts": {
            "0.5pct": false,
            "1.0pct": false,
            "2.0pct": false,
            "5.0pct": false,
            "10.0pct": false
          },
          "validity": {
            "window_days": 3,
            "valid_from": "2026-07-10T00:00:00Z",
            "valid_to": "2026-07-12T23:59:59Z"
          },
          "probability_seismic": 0.18008,
          "gps_reliability": 0.25,
          "boost": 0.0
        }
      }
    },
    {
      "zone_id": "Z_35_135",
      "name": "Osaka-Kobe",
      "pop_millions": 60,
      "tiers": {
        "T1": {
          "probability": 0.649211,
          "alerts": {
            "0.5pct": false,
            "1.0pct": false,
            "2.0pct": false,
            "5.0pct": false,
            "10.0pct": false
          },
          "validity": {
            "window_days": 2,
            "valid_from": "2026-07-10T00:00:00Z",
            "valid_to": "2026-07-11T23:59:59Z"
          },
          "probability_seismic": 0.649211,
          "gps_reliability": 0.25,
          "boost": 0.0
        },
        "T2": {
          "probability": 0.407,
          "alerts": {
            "0.5pct": false,
            "1.0pct": false,
            "2.0pct": false,
            "5.0pct": false,
            "10.0pct": false
          },
          "validity": {
            "window_days": 2,
            "valid_from": "2026-07-10T00:00:00Z",
            "valid_to": "2026-07-11T23:59:59Z"
          },
          "probability_seismic": 0.407,
          "gps_reliability": 0.25,
          "boost": 0.0
        },
        "T3": {
          "probability": 0.312809,
          "alerts": {
            "0.5pct": false,
            "1.0pct": false,
            "2.0pct": false,
            "5.0pct": false,
            "10.0pct": false
          },
          "validity": {
            "window_days": 3,
            "valid_from": "2026-07-10T00:00:00Z",
            "valid_to": "2026-07-12T23:59:59Z"
          },
          "probability_seismic": 0.312809,
          "gps_reliability": 0.25,
          "boost": -0.0
        },
        "T4": {
          "probability": 0.265285,
          "alerts": {
            "0.5pct": false,
            "1.0pct": false,
            "2.0pct": false,
            "5.0pct": false,
            "10.0pct": false
          },
          "validity": {
            "window_days": 3,
            "valid_from": "2026-07-10T00:00:00Z",
            "valid_to": "2026-07-12T23:59:59Z"
          },
          "probability_seismic": 0.265285,
          "gps_reliability": 0.25,
          "boost": -0.0
        }
      }
    },
    {
      "zone_id": "Z_35_140",
      "name": "Tokyo-Kanto",
      "pop_millions": 39,
      "tiers": {
        "T1": {
          "probability": 0.83494,
          "alerts": {
            "0.5pct": false,
            "1.0pct": false,
            "2.0pct": false,
            "5.0pct": false,
            "10.0pct": false
          },
          "validity": {
            "window_days": 2,
            "valid_from": "2026-07-10T00:00:00Z",
            "valid_to": "2026-07-11T23:59:59Z"
          },
          "probability_seismic": 0.83494,
          "gps_reliability": 0.396,
          "boost": 0.0
        },
        "T2": {
          "probability": 0.456574,
          "alerts": {
            "0.5pct": false,
            "1.0pct": false,
            "2.0pct": false,
            "5.0pct": false,
            "10.0pct": false
          },
          "validity": {
            "window_days": 2,
            "valid_from": "2026-07-10T00:00:00Z",
            "valid_to": "2026-07-11T23:59:59Z"
          },
          "probability_seismic": 0.456574,
          "gps_reliability": 0.396,
          "boost": 0.0
        },
        "T3": {
          "probability": 0.367416,
          "alerts": {
            "0.5pct": false,
            "1.0pct": false,
            "2.0pct": false,
            "5.0pct": false,
            "10.0pct": false
          },
          "validity": {
            "window_days": 3,
            "valid_from": "2026-07-10T00:00:00Z",
            "valid_to": "2026-07-12T23:59:59Z"
          },
          "probability_seismic": 0.367416,
          "gps_reliability": 0.396,
          "boost": 0.0
        },
        "T4": {
          "probability": 0.351891,
          "alerts": {
            "0.5pct": false,
            "1.0pct": false,
            "2.0pct": false,
            "5.0pct": false,
            "10.0pct": false
          },
          "validity": {
            "window_days": 3,
            "valid_from": "2026-07-10T00:00:00Z",
            "valid_to": "2026-07-12T23:59:59Z"
          },
          "probability_seismic": 0.351891,
          "gps_reliability": 0.396,
          "boost": 0.0
        }
      }
    },
    {
      "zone_id": "Z_40_130",
      "name": "Z_40_130",
      "pop_millions": 0,
      "tiers": {
        "T1": {
          "probability": 0.022217,
          "alerts": {
            "0.5pct": false,
            "1.0pct": false,
            "2.0pct": false,
            "5.0pct": false,
            "10.0pct": false
          },
          "validity": {
            "window_days": 2,
            "valid_from": "2026-07-10T00:00:00Z",
            "valid_to": "2026-07-11T23:59:59Z"
          },
          "probability_seismic": 0.022217,
          "gps_reliability": 0.5,
          "boost": 0.0
        },
        "T2": {
          "probability": 0.206436,
          "alerts": {
            "0.5pct": false,
            "1.0pct": false,
            "2.0pct": false,
            "5.0pct": false,
            "10.0pct": false
          },
          "validity": {
            "window_days": 2,
            "valid_from": "2026-07-10T00:00:00Z",
            "valid_to": "2026-07-11T23:59:59Z"
          },
          "probability_seismic": 0.206436,
          "gps_reliability": 0.5,
          "boost": -0.0
        },
        "T3": {
          "probability": 0.293653,
          "alerts": {
            "0.5pct": false,
            "1.0pct": false,
            "2.0pct": false,
            "5.0pct": false,
            "10.0pct": false
          },
          "validity": {
            "window_days": 3,
            "valid_from": "2026-07-10T00:00:00Z",
            "valid_to": "2026-07-12T23:59:59Z"
          },
          "probability_seismic": 0.293653,
          "gps_reliability": 0.5,
          "boost": 0.0
        },
        "T4": {
          "probability": 0.271464,
          "alerts": {
            "0.5pct": false,
            "1.0pct": false,
            "2.0pct": false,
            "5.0pct": false,
            "10.0pct": false
          },
          "validity": {
            "window_days": 3,
            "valid_from": "2026-07-10T00:00:00Z",
            "valid_to": "2026-07-12T23:59:59Z"
          },
          "probability_seismic": 0.271464,
          "gps_reliability": 0.5,
          "boost": 0.0
        }
      }
    },
    {
      "zone_id": "Z_40_135",
      "name": "Niigata",
      "pop_millions": 8,
      "tiers": {
        "T1": {
          "probability": 0.247961,
          "alerts": {
            "0.5pct": false,
            "1.0pct": false,
            "2.0pct": false,
            "5.0pct": false,
            "10.0pct": false
          },
          "validity": {
            "window_days": 2,
            "valid_from": "2026-07-10T00:00:00Z",
            "valid_to": "2026-07-11T23:59:59Z"
          },
          "probability_seismic": 0.247961,
          "gps_reliability": 0.25,
          "boost": 0.0
        },
        "T2": {
          "probability": 0.150641,
          "alerts": {
            "0.5pct": false,
            "1.0pct": false,
            "2.0pct": false,
            "5.0pct": false,
            "10.0pct": false
          },
          "validity": {
            "window_days": 2,
            "valid_from": "2026-07-10T00:00:00Z",
            "valid_to": "2026-07-11T23:59:59Z"
          },
          "probability_seismic": 0.150641,
          "gps_reliability": 0.25,
          "boost": -0.0
        },
        "T3": {
          "probability": 0.154656,
          "alerts": {
            "0.5pct": false,
            "1.0pct": false,
            "2.0pct": false,
            "5.0pct": false,
            "10.0pct": false
          },
          "validity": {
            "window_days": 3,
            "valid_from": "2026-07-10T00:00:00Z",
            "valid_to": "2026-07-12T23:59:59Z"
          },
          "probability_seismic": 0.154656,
          "gps_reliability": 0.25,
          "boost": 0.0
        },
        "T4": {
          "probability": 0.104108,
          "alerts": {
            "0.5pct": false,
            "1.0pct": false,
            "2.0pct": false,
            "5.0pct": false,
            "10.0pct": false
          },
          "validity": {
            "window_days": 3,
            "valid_from": "2026-07-10T00:00:00Z",
            "valid_to": "2026-07-12T23:59:59Z"
          },
          "probability_seismic": 0.104108,
          "gps_reliability": 0.25,
          "boost": 0.0
        }
      }
    },
    {
      "zone_id": "Z_40_140",
      "name": "Hokkaido-S",
      "pop_millions": 4,
      "tiers": {
        "T1": {
          "probability": 0.903789,
          "alerts": {
            "0.5pct": false,
            "1.0pct": false,
            "2.0pct": false,
            "5.0pct": false,
            "10.0pct": false
          },
          "validity": {
            "window_days": 2,
            "valid_from": "2026-07-10T00:00:00Z",
            "valid_to": "2026-07-11T23:59:59Z"
          },
          "probability_seismic": 0.903789,
          "gps_reliability": 0.58,
          "boost": 0.0
        },
        "T2": {
          "probability": 0.625838,
          "alerts": {
            "0.5pct": false,
            "1.0pct": false,
            "2.0pct": false,
            "5.0pct": false,
            "10.0pct": false
          },
          "validity": {
            "window_days": 2,
            "valid_from": "2026-07-10T00:00:00Z",
            "valid_to": "2026-07-11T23:59:59Z"
          },
          "probability_seismic": 0.625838,
          "gps_reliability": 0.58,
          "boost": 0.0
        },
        "T3": {
          "probability": 0.57639,
          "alerts": {
            "0.5pct": false,
            "1.0pct": false,
            "2.0pct": false,
            "5.0pct": false,
            "10.0pct": false
          },
          "validity": {
            "window_days": 3,
            "valid_from": "2026-07-10T00:00:00Z",
            "valid_to": "2026-07-12T23:59:59Z"
          },
          "probability_seismic": 0.57639,
          "gps_reliability": 0.58,
          "boost": 0.0
        },
        "T4": {
          "probability": 0.569781,
          "alerts": {
            "0.5pct": false,
            "1.0pct": false,
            "2.0pct": false,
            "5.0pct": false,
            "10.0pct": false
          },
          "validity": {
            "window_days": 3,
            "valid_from": "2026-07-10T00:00:00Z",
            "valid_to": "2026-07-12T23:59:59Z"
          },
          "probability_seismic": 0.569781,
          "gps_reliability": 0.58,
          "boost": 0.0
        }
      }
    },
    {
      "zone_id": "Z_40_145",
      "name": "Hokkaido-E",
      "pop_millions": 5,
      "tiers": {
        "T1": {
          "probability": 0.579054,
          "alerts": {
            "0.5pct": false,
            "1.0pct": false,
            "2.0pct": false,
            "5.0pct": false,
            "10.0pct": false
          },
          "validity": {
            "window_days": 2,
            "valid_from": "2026-07-10T00:00:00Z",
            "valid_to": "2026-07-11T23:59:59Z"
          },
          "probability_seismic": 0.579054,
          "gps_reliability": 0.952,
          "boost": 0.0
        },
        "T2": {
          "probability": 0.426428,
          "alerts": {
            "0.5pct": false,
            "1.0pct": false,
            "2.0pct": false,
            "5.0pct": false,
            "10.0pct": false
          },
          "validity": {
            "window_days": 2,
            "valid_from": "2026-07-10T00:00:00Z",
            "valid_to": "2026-07-11T23:59:59Z"
          },
          "probability_seismic": 0.426428,
          "gps_reliability": 0.952,
          "boost": 0.0
        },
        "T3": {
          "probability": 0.354206,
          "alerts": {
            "0.5pct": false,
            "1.0pct": false,
            "2.0pct": false,
            "5.0pct": false,
            "10.0pct": false
          },
          "validity": {
            "window_days": 3,
            "valid_from": "2026-07-10T00:00:00Z",
            "valid_to": "2026-07-12T23:59:59Z"
          },
          "probability_seismic": 0.354206,
          "gps_reliability": 0.952,
          "boost": 0.0
        },
        "T4": {
          "probability": 0.31672,
          "alerts": {
            "0.5pct": false,
            "1.0pct": false,
            "2.0pct": false,
            "5.0pct": false,
            "10.0pct": false
          },
          "validity": {
            "window_days": 3,
            "valid_from": "2026-07-10T00:00:00Z",
            "valid_to": "2026-07-12T23:59:59Z"
          },
          "probability_seismic": 0.31672,
          "gps_reliability": 0.952,
          "boost": 0.0
        }
      }
    },
    {
      "zone_id": "Z_40_150",
      "name": "Z_40_150",
      "pop_millions": 0,
      "tiers": {
        "T1": {
          "probability": 0.065532,
          "alerts": {
            "0.5pct": false,
            "1.0pct": false,
            "2.0pct": false,
            "5.0pct": false,
            "10.0pct": false
          },
          "validity": {
            "window_days": 2,
            "valid_from": "2026-07-10T00:00:00Z",
            "valid_to": "2026-07-11T23:59:59Z"
          }
        },
        "T2": {
          "probability": 0.314227,
          "alerts": {
            "0.5pct": false,
            "1.0pct": false,
            "2.0pct": false,
            "5.0pct": false,
            "10.0pct": true
          },
          "validity": {
            "window_days": 2,
            "valid_from": "2026-07-10T00:00:00Z",
            "valid_to": "2026-07-11T23:59:59Z"
          }
        },
        "T3": {
          "probability": 0.391465,
          "alerts": {
            "0.5pct": false,
            "1.0pct": false,
            "2.0pct": false,
            "5.0pct": true,
            "10.0pct": true
          },
          "validity": {
            "window_days": 3,
            "valid_from": "2026-07-10T00:00:00Z",
            "valid_to": "2026-07-12T23:59:59Z"
          }
        },
        "T4": {
          "probability": 0.31041,
          "alerts": {
            "0.5pct": false,
            "1.0pct": false,
            "2.0pct": false,
            "5.0pct": true,
            "10.0pct": true
          },
          "validity": {
            "window_days": 3,
            "valid_from": "2026-07-10T00:00:00Z",
            "valid_to": "2026-07-12T23:59:59Z"
          }
        }
      }
    },
    {
      "zone_id": "Z_45_140",
      "name": "Z_45_140",
      "pop_millions": 0,
      "tiers": {
        "T1": {
          "probability": 0.028027,
          "alerts": {
            "0.5pct": false,
            "1.0pct": false,
            "2.0pct": false,
            "5.0pct": false,
            "10.0pct": false
          },
          "validity": {
            "window_days": 2,
            "valid_from": "2026-07-10T00:00:00Z",
            "valid_to": "2026-07-11T23:59:59Z"
          },
          "probability_seismic": 0.028027,
          "gps_reliability": 0.25,
          "boost": 0.0
        },
        "T2": {
          "probability": 0.241958,
          "alerts": {
            "0.5pct": false,
            "1.0pct": false,
            "2.0pct": false,
            "5.0pct": false,
            "10.0pct": false
          },
          "validity": {
            "window_days": 2,
            "valid_from": "2026-07-10T00:00:00Z",
            "valid_to": "2026-07-11T23:59:59Z"
          },
          "probability_seismic": 0.241958,
          "gps_reliability": 0.25,
          "boost": -0.0
        },
        "T3": {
          "probability": 0.334699,
          "alerts": {
            "0.5pct": false,
            "1.0pct": false,
            "2.0pct": false,
            "5.0pct": false,
            "10.0pct": false
          },
          "validity": {
            "window_days": 3,
            "valid_from": "2026-07-10T00:00:00Z",
            "valid_to": "2026-07-12T23:59:59Z"
          },
          "probability_seismic": 0.334699,
          "gps_reliability": 0.25,
          "boost": 0.0
        },
        "T4": {
          "probability": 0.312042,
          "alerts": {
            "0.5pct": false,
            "1.0pct": false,
            "2.0pct": false,
            "5.0pct": false,
            "10.0pct": false
          },
          "validity": {
            "window_days": 3,
            "valid_from": "2026-07-10T00:00:00Z",
            "valid_to": "2026-07-12T23:59:59Z"
          },
          "probability_seismic": 0.312042,
          "gps_reliability": 0.25,
          "boost": 0.0
        }
      }
    },
    {
      "zone_id": "Z_45_145",
      "name": "Kuril-South",
      "pop_millions": 5,
      "tiers": {
        "T1": {
          "probability": 0.058916,
          "alerts": {
            "0.5pct": false,
            "1.0pct": false,
            "2.0pct": false,
            "5.0pct": false,
            "10.0pct": false
          },
          "validity": {
            "window_days": 2,
            "valid_from": "2026-07-10T00:00:00Z",
            "valid_to": "2026-07-11T23:59:59Z"
          },
          "probability_seismic": 0.058916,
          "gps_reliability": 0.25,
          "boost": 0.0
        },
        "T2": {
          "probability": 0.312586,
          "alerts": {
            "0.5pct": false,
            "1.0pct": false,
            "2.0pct": false,
            "5.0pct": false,
            "10.0pct": false
          },
          "validity": {
            "window_days": 2,
            "valid_from": "2026-07-10T00:00:00Z",
            "valid_to": "2026-07-11T23:59:59Z"
          },
          "probability_seismic": 0.312586,
          "gps_reliability": 0.25,
          "boost": 0.0
        },
        "T3": {
          "probability": 0.400673,
          "alerts": {
            "0.5pct": false,
            "1.0pct": false,
            "2.0pct": false,
            "5.0pct": false,
            "10.0pct": false
          },
          "validity": {
            "window_days": 3,
            "valid_from": "2026-07-10T00:00:00Z",
            "valid_to": "2026-07-12T23:59:59Z"
          },
          "probability_seismic": 0.400673,
          "gps_reliability": 0.25,
          "boost": 0.0
        },
        "T4": {
          "probability": 0.36049,
          "alerts": {
            "0.5pct": false,
            "1.0pct": false,
            "2.0pct": false,
            "5.0pct": false,
            "10.0pct": false
          },
          "validity": {
            "window_days": 3,
            "valid_from": "2026-07-10T00:00:00Z",
            "valid_to": "2026-07-12T23:59:59Z"
          },
          "probability_seismic": 0.36049,
          "gps_reliability": 0.25,
          "boost": 0.0
        }
      }
    },
    {
      "zone_id": "Z_45_150",
      "name": "Z_45_150",
      "pop_millions": 0,
      "tiers": {
        "T1": {
          "probability": 0.164681,
          "alerts": {
            "0.5pct": false,
            "1.0pct": false,
            "2.0pct": false,
            "5.0pct": false,
            "10.0pct": false
          },
          "validity": {
            "window_days": 2,
            "valid_from": "2026-07-10T00:00:00Z",
            "valid_to": "2026-07-11T23:59:59Z"
          }
        },
        "T2": {
          "probability": 0.355741,
          "alerts": {
            "0.5pct": false,
            "1.0pct": false,
            "2.0pct": false,
            "5.0pct": false,
            "10.0pct": false
          },
          "validity": {
            "window_days": 2,
            "valid_from": "2026-07-10T00:00:00Z",
            "valid_to": "2026-07-11T23:59:59Z"
          }
        },
        "T3": {
          "probability": 0.363875,
          "alerts": {
            "0.5pct": false,
            "1.0pct": false,
            "2.0pct": false,
            "5.0pct": false,
            "10.0pct": false
          },
          "validity": {
            "window_days": 3,
            "valid_from": "2026-07-10T00:00:00Z",
            "valid_to": "2026-07-12T23:59:59Z"
          }
        },
        "T4": {
          "probability": 0.237643,
          "alerts": {
            "0.5pct": false,
            "1.0pct": false,
            "2.0pct": false,
            "5.0pct": false,
            "10.0pct": false
          },
          "validity": {
            "window_days": 3,
            "valid_from": "2026-07-10T00:00:00Z",
            "valid_to": "2026-07-12T23:59:59Z"
          }
        }
      }
    },
    {
      "zone_id": "Z_45_155",
      "name": "Z_45_155",
      "pop_millions": 0,
      "tiers": {
        "T1": {
          "probability": 0.024422,
          "alerts": {
            "0.5pct": false,
            "1.0pct": false,
            "2.0pct": false,
            "5.0pct": false,
            "10.0pct": false
          },
          "validity": {
            "window_days": 2,
            "valid_from": "2026-07-10T00:00:00Z",
            "valid_to": "2026-07-11T23:59:59Z"
          }
        },
        "T2": {
          "probability": 0.220824,
          "alerts": {
            "0.5pct": false,
            "1.0pct": false,
            "2.0pct": false,
            "5.0pct": false,
            "10.0pct": false
          },
          "validity": {
            "window_days": 2,
            "valid_from": "2026-07-10T00:00:00Z",
            "valid_to": "2026-07-11T23:59:59Z"
          }
        },
        "T3": {
          "probability": 0.30913,
          "alerts": {
            "0.5pct": false,
            "1.0pct": false,
            "2.0pct": false,
            "5.0pct": false,
            "10.0pct": false
          },
          "validity": {
            "window_days": 3,
            "valid_from": "2026-07-10T00:00:00Z",
            "valid_to": "2026-07-12T23:59:59Z"
          }
        },
        "T4": {
          "probability": 0.283009,
          "alerts": {
            "0.5pct": false,
            "1.0pct": false,
            "2.0pct": false,
            "5.0pct": false,
            "10.0pct": false
          },
          "validity": {
            "window_days": 3,
            "valid_from": "2026-07-10T00:00:00Z",
            "valid_to": "2026-07-12T23:59:59Z"
          }
        }
      }
    },
    {
      "zone_id": "Z_50_150",
      "name": "Z_50_150",
      "pop_millions": 0,
      "tiers": {
        "T1": {
          "probability": 0.144435,
          "alerts": {
            "0.5pct": true,
            "1.0pct": true,
            "2.0pct": true,
            "5.0pct": true,
            "10.0pct": true
          },
          "validity": {
            "window_days": 2,
            "valid_from": "2026-07-10T00:00:00Z",
            "valid_to": "2026-07-11T23:59:59Z"
          }
        },
        "T2": {
          "probability": 0.212585,
          "alerts": {
            "0.5pct": false,
            "1.0pct": false,
            "2.0pct": false,
            "5.0pct": false,
            "10.0pct": false
          },
          "validity": {
            "window_days": 2,
            "valid_from": "2026-07-10T00:00:00Z",
            "valid_to": "2026-07-11T23:59:59Z"
          }
        },
        "T3": {
          "probability": 0.227,
          "alerts": {
            "0.5pct": false,
            "1.0pct": false,
            "2.0pct": false,
            "5.0pct": false,
            "10.0pct": false
          },
          "validity": {
            "window_days": 3,
            "valid_from": "2026-07-10T00:00:00Z",
            "valid_to": "2026-07-12T23:59:59Z"
          }
        },
        "T4": {
          "probability": 0.25117,
          "alerts": {
            "0.5pct": false,
            "1.0pct": false,
            "2.0pct": false,
            "5.0pct": false,
            "10.0pct": false
          },
          "validity": {
            "window_days": 3,
            "valid_from": "2026-07-10T00:00:00Z",
            "valid_to": "2026-07-12T23:59:59Z"
          }
        }
      }
    },
    {
      "zone_id": "Z_50_155",
      "name": "Z_50_155",
      "pop_millions": 0,
      "tiers": {
        "T1": {
          "probability": 0.023844,
          "alerts": {
            "0.5pct": false,
            "1.0pct": false,
            "2.0pct": false,
            "5.0pct": false,
            "10.0pct": false
          },
          "validity": {
            "window_days": 2,
            "valid_from": "2026-07-10T00:00:00Z",
            "valid_to": "2026-07-11T23:59:59Z"
          },
          "probability_seismic": 0.023844,
          "gps_reliability": 0.25,
          "boost": -0.0
        },
        "T2": {
          "probability": 0.218952,
          "alerts": {
            "0.5pct": false,
            "1.0pct": false,
            "2.0pct": false,
            "5.0pct": false,
            "10.0pct": false
          },
          "validity": {
            "window_days": 2,
            "valid_from": "2026-07-10T00:00:00Z",
            "valid_to": "2026-07-11T23:59:59Z"
          },
          "probability_seismic": 0.218952,
          "gps_reliability": 0.25,
          "boost": 0.0
        },
        "T3": {
          "probability": 0.308578,
          "alerts": {
            "0.5pct": false,
            "1.0pct": false,
            "2.0pct": false,
            "5.0pct": false,
            "10.0pct": false
          },
          "validity": {
            "window_days": 3,
            "valid_from": "2026-07-10T00:00:00Z",
            "valid_to": "2026-07-12T23:59:59Z"
          },
          "probability_seismic": 0.308578,
          "gps_reliability": 0.25,
          "boost": 0.0
        },
        "T4": {
          "probability": 0.283279,
          "alerts": {
            "0.5pct": false,
            "1.0pct": false,
            "2.0pct": false,
            "5.0pct": false,
            "10.0pct": false
          },
          "validity": {
            "window_days": 3,
            "valid_from": "2026-07-10T00:00:00Z",
            "valid_to": "2026-07-12T23:59:59Z"
          },
          "probability_seismic": 0.283279,
          "gps_reliability": 0.25,
          "boost": 0.0
        }
      }
    }
  ],
  "summary": {
    "total_zones": 29,
    "alerts_by_tier": {
      "T1": 1,
      "T2": 0,
      "T3": 2,
      "T4": 2
    }
  }
}